labelcsv/__init__.py
labelcsv/__main__.py
labelcsv/labelcsv.py
labelcsv-0.1.2.dist-info/METADATA
labelcsv-0.1.2.dist-info/WHEEL
labelcsv-0.1.2.dist-info/entry_points.txt
labelcsv-0.1.2.dist-info/top_level.txt
labelcsv-0.1.2.dist-info/RECORD
