Metadata-Version: 2.1
Name: labelcsv
Version: 0.1.2
Summary: Label a csv file directly in your terminal.
Author: jtheol
Author-email: 
Keywords: python,dataset,label,csv,text,classification
Classifier: Development Status :: 1 - Planning
Classifier: Intended Audience :: Developers
Classifier: Programming Language :: Python :: 3
Classifier: Operating System :: Unix
Classifier: Operating System :: MacOS :: MacOS X
Classifier: Operating System :: Microsoft :: Windows
Requires-Dist: pandas
Requires-Dist: inquirerpy
Requires-Dist: colorama
Requires-Dist: plotext
